odoo8_addon_auth_signup_verify_email-8.0.1.0.0.99.dev17-py2.7-nspkg.pth
odoo8_addon_auth_signup_verify_email-8.0.1.0.0.99.dev17.dist-info/METADATA
odoo8_addon_auth_signup_verify_email-8.0.1.0.0.99.dev17.dist-info/RECORD
odoo8_addon_auth_signup_verify_email-8.0.1.0.0.99.dev17.dist-info/WHEEL
odoo8_addon_auth_signup_verify_email-8.0.1.0.0.99.dev17.dist-info/namespace_packages.txt
odoo8_addon_auth_signup_verify_email-8.0.1.0.0.99.dev17.dist-info/top_level.txt
odoo_addons/auth_signup_verify_email/README.rst
odoo_addons/auth_signup_verify_email/__init__.py
odoo_addons/auth_signup_verify_email/__openerp__.py
odoo_addons/auth_signup_verify_email/controllers/__init__.py
odoo_addons/auth_signup_verify_email/controllers/main.py
odoo_addons/auth_signup_verify_email/i18n/auth_signup_verify_email.pot
odoo_addons/auth_signup_verify_email/i18n/ca.po
odoo_addons/auth_signup_verify_email/i18n/de.po
odoo_addons/auth_signup_verify_email/i18n/es.po
odoo_addons/auth_signup_verify_email/i18n/es_ES.po
odoo_addons/auth_signup_verify_email/i18n/fr.po
odoo_addons/auth_signup_verify_email/i18n/it.po
odoo_addons/auth_signup_verify_email/i18n/pt_BR.po
odoo_addons/auth_signup_verify_email/i18n/sl.po
odoo_addons/auth_signup_verify_email/i18n/tr.po
odoo_addons/auth_signup_verify_email/static/description/icon.png
odoo_addons/auth_signup_verify_email/static/description/icon.svg
odoo_addons/auth_signup_verify_email/views/signup.xml
